Metadata-Version: 2.1
Name: topsis34
Version: 1.0.0
Summary: A Python package for topsis.
Home-page: https://github.com/ramneet99
Author: Ramneet Singh
Author-email: ramneet2511@gmail.com
License: MIT
Platform: UNKNOWN
Classifier: License :: OSI Approved :: MIT License
Classifier: Programming Language :: Python :: 3
Classifier: Programming Language :: Python :: 3.7
